toolslmself/__init__.py
toolslmself/egg.py
toolslmself/kits.py
toolslmself/mycolor.py
toolslmself/office.py
tools_lmself-0.0.14.dist-info/METADATA
tools_lmself-0.0.14.dist-info/WHEEL
tools_lmself-0.0.14.dist-info/top_level.txt
tools_lmself-0.0.14.dist-info/RECORD
