Metadata-Version: 2.1
Name: tools-lmself
Version: 0.0.14
Summary: 工具包
Home-page: UNKNOWN
Author: upcoder
License: UNKNOWN
Platform: UNKNOWN
Classifier: Programming Language :: Python :: 3
Classifier: License :: OSI Approved :: MIT License
Classifier: Operating System :: OS Independent
Requires-Dist: Pillow (==9.0.0)
Requires-Dist: selenium (==4.2.0)
Requires-Dist: requests (==2.28.0)
Requires-Dist: python-docx (==0.8.11)
Requires-Dist: openpyxl (==3.0.10)
